{"v":3,"stories":{"accordionlist--accordion-list":{"id":"accordionlist--accordion-list","name":"Accordion List","title":"AccordionList","importPath":"./src/stories/AccordionList.stories.tsx","tags":["story"],"kind":"AccordionList","story":"Accordion List","parameters":{"__id":"accordionlist--accordion-list","docsOnly":false,"fileName":"./src/stories/AccordionList.stories.tsx"}},"accordionlist--accordion-list-styling":{"id":"accordionlist--accordion-list-styling","name":"Accordion List Styling","title":"AccordionList","importPath":"./src/stories/AccordionList.stories.tsx","tags":["story"],"kind":"AccordionList","story":"Accordion List Styling","parameters":{"__id":"accordionlist--accordion-list-styling","docsOnly":false,"fileName":"./src/stories/AccordionList.stories.tsx"}},"actioncards--action-cards":{"id":"actioncards--action-cards","name":"Action Cards","title":"ActionCards","importPath":"./src/stories/Actioncards.stories.tsx","tags":["story"],"kind":"ActionCards","story":"Action Cards","parameters":{"__id":"actioncards--action-cards","docsOnly":false,"fileName":"./src/stories/Actioncards.stories.tsx"}},"alert--alert":{"id":"alert--alert","name":"Alert","title":"Alert","importPath":"./src/stories/Alert.stories.tsx","tags":["story"],"kind":"Alert","story":"Alert","parameters":{"__id":"alert--alert","docsOnly":false,"fileName":"./src/stories/Alert.stories.tsx"}},"articlecards--article-cards":{"id":"articlecards--article-cards","name":"Article Cards","title":"ArticleCards","importPath":"./src/stories/ArticleCards.stories.tsx","tags":["story"],"kind":"ArticleCards","story":"Article Cards","parameters":{"__id":"articlecards--article-cards","docsOnly":false,"fileName":"./src/stories/ArticleCards.stories.tsx"}},"articlecarousel--article-carousel":{"id":"articlecarousel--article-carousel","name":"Article Carousel","title":"ArticleCarousel","importPath":"./src/stories/ArticleCarousel.stories.tsx","tags":["story"],"kind":"ArticleCarousel","story":"Article Carousel","parameters":{"__id":"articlecarousel--article-carousel","docsOnly":false,"fileName":"./src/stories/ArticleCarousel.stories.tsx"}},"articlemeta--article-meta":{"id":"articlemeta--article-meta","name":"Article Meta","title":"ArticleMeta","importPath":"./src/stories/ArticleMeta.stories.tsx","tags":["story"],"kind":"ArticleMeta","story":"Article Meta","parameters":{"__id":"articlemeta--article-meta","docsOnly":false,"fileName":"./src/stories/ArticleMeta.stories.tsx"}},"attention--attention":{"id":"attention--attention","name":"Attention","title":"Attention","importPath":"./src/stories/Attention.stories.tsx","tags":["story"],"kind":"Attention","story":"Attention","parameters":{"__id":"attention--attention","docsOnly":false,"fileName":"./src/stories/Attention.stories.tsx"}},"forms-autosuggestsearch--autosuggest-search":{"id":"forms-autosuggestsearch--autosuggest-search","name":"Autosuggest Search","title":"Forms/AutosuggestSearch","importPath":"./src/stories/AutosuggestSearch.stories.tsx","tags":["story"],"kind":"Forms/AutosuggestSearch","story":"Autosuggest Search","parameters":{"__id":"forms-autosuggestsearch--autosuggest-search","docsOnly":false,"fileName":"./src/stories/AutosuggestSearch.stories.tsx"}},"basictable--basic-table":{"id":"basictable--basic-table","name":"Basic Table","title":"BasicTable","importPath":"./src/stories/BasicTable.stories.tsx","tags":["story"],"kind":"BasicTable","story":"Basic Table","parameters":{"__id":"basictable--basic-table","docsOnly":false,"fileName":"./src/stories/BasicTable.stories.tsx"}},"bgbox--bg-box":{"id":"bgbox--bg-box","name":"Bg Box","title":"BgBox","importPath":"./src/stories/BgBox.stories.tsx","tags":["story"],"kind":"BgBox","story":"Bg Box","parameters":{"__id":"bgbox--bg-box","docsOnly":false,"fileName":"./src/stories/BgBox.stories.tsx"}},"bling--bling":{"id":"bling--bling","name":"Bling","title":"Bling","importPath":"./src/stories/Bling.stories.tsx","tags":["story"],"kind":"Bling","story":"Bling","parameters":{"__id":"bling--bling","docsOnly":false,"fileName":"./src/stories/Bling.stories.tsx"}},"text-blockquote--block-quote":{"id":"text-blockquote--block-quote","name":"Block Quote","title":"text/BlockQuote","importPath":"./src/stories/Blockquote.stories.tsx","tags":["story"],"kind":"text/BlockQuote","story":"Block Quote","parameters":{"__id":"text-blockquote--block-quote","docsOnly":false,"fileName":"./src/stories/Blockquote.stories.tsx"}},"layout-breadcrumbs--bread-crumbs":{"id":"layout-breadcrumbs--bread-crumbs","name":"Bread Crumbs","title":"Layout/BreadCrumbs","importPath":"./src/stories/BreadCrumbs.stories.tsx","tags":["story"],"kind":"Layout/BreadCrumbs","story":"Bread Crumbs","parameters":{"__id":"layout-breadcrumbs--bread-crumbs","docsOnly":false,"fileName":"./src/stories/BreadCrumbs.stories.tsx"}},"buttons-buttonback--button-back":{"id":"buttons-buttonback--button-back","name":"ButtonBack","title":"buttons/ButtonBack","importPath":"./src/stories/ButtonBack.stories.tsx","tags":["story"],"kind":"buttons/ButtonBack","story":"ButtonBack","parameters":{"__id":"buttons-buttonback--button-back","docsOnly":false,"fileName":"./src/stories/ButtonBack.stories.tsx"}},"buttons-buttonbar--button-bar":{"id":"buttons-buttonbar--button-bar","name":"Button Bar","title":"buttons/ButtonBar","importPath":"./src/stories/ButtonBar.stories.tsx","tags":["story"],"kind":"buttons/ButtonBar","story":"Button Bar","parameters":{"__id":"buttons-buttonbar--button-bar","docsOnly":false,"fileName":"./src/stories/ButtonBar.stories.tsx"}},"buttons-buttons--buttons":{"id":"buttons-buttons--buttons","name":"Buttons","title":"buttons/Buttons","importPath":"./src/stories/Buttons.stories.tsx","tags":["story"],"kind":"buttons/Buttons","story":"Buttons","parameters":{"__id":"buttons-buttons--buttons","docsOnly":false,"fileName":"./src/stories/Buttons.stories.tsx"}},"carousel--carousel":{"id":"carousel--carousel","name":"Carousel","title":"Carousel","importPath":"./src/stories/Carousel.stories.tsx","tags":["story"],"kind":"Carousel","story":"Carousel","parameters":{"__id":"carousel--carousel","docsOnly":false,"fileName":"./src/stories/Carousel.stories.tsx"}},"grid--center-column":{"id":"grid--center-column","name":"Center Column","title":"Grid","importPath":"./src/stories/CenterColumn.stories.tsx","tags":["story"],"kind":"Grid","story":"Center Column","parameters":{"__id":"grid--center-column","docsOnly":false,"fileName":"./src/stories/CenterColumn.stories.tsx"}},"forms-checkbox-radio--radio":{"id":"forms-checkbox-radio--radio","name":"Radio","title":"Forms/Checkbox & Radio","importPath":"./src/stories/CheckboxAndRadio.stories.tsx","tags":["story"],"kind":"Forms/Checkbox & Radio","story":"Radio","parameters":{"__id":"forms-checkbox-radio--radio","docsOnly":false,"fileName":"./src/stories/CheckboxAndRadio.stories.tsx"}},"forms-checkbox-radio--checkbox":{"id":"forms-checkbox-radio--checkbox","name":"Checkbox","title":"Forms/Checkbox & Radio","importPath":"./src/stories/CheckboxAndRadio.stories.tsx","tags":["story"],"kind":"Forms/Checkbox & Radio","story":"Checkbox","parameters":{"__id":"forms-checkbox-radio--checkbox","docsOnly":false,"fileName":"./src/stories/CheckboxAndRadio.stories.tsx"}},"forms-checkbox-radio--checkbox-group":{"id":"forms-checkbox-radio--checkbox-group","name":"Checkbox Group","title":"Forms/Checkbox & Radio","importPath":"./src/stories/CheckboxAndRadio.stories.tsx","tags":["story"],"kind":"Forms/Checkbox & Radio","story":"Checkbox Group","parameters":{"__id":"forms-checkbox-radio--checkbox-group","docsOnly":false,"fileName":"./src/stories/CheckboxAndRadio.stories.tsx"}},"forms-checkbox-radio--radio-group":{"id":"forms-checkbox-radio--radio-group","name":"Radio Group","title":"Forms/Checkbox & Radio","importPath":"./src/stories/CheckboxAndRadio.stories.tsx","tags":["story"],"kind":"Forms/Checkbox & Radio","story":"Radio Group","parameters":{"__id":"forms-checkbox-radio--radio-group","docsOnly":false,"fileName":"./src/stories/CheckboxAndRadio.stories.tsx"}},"forms-checkbox-radio--styling-tests":{"id":"forms-checkbox-radio--styling-tests","name":"Styling Tests","title":"Forms/Checkbox & Radio","importPath":"./src/stories/CheckboxAndRadio.stories.tsx","tags":["story"],"kind":"Forms/Checkbox & Radio","story":"Styling Tests","parameters":{"__id":"forms-checkbox-radio--styling-tests","docsOnly":false,"fileName":"./src/stories/CheckboxAndRadio.stories.tsx"}},"forms-checkbox-radio-buttons--checkbox-button":{"id":"forms-checkbox-radio-buttons--checkbox-button","name":"CheckboxButton","title":"Forms/Checkbox & Radio Buttons","importPath":"./src/stories/CheckboxAndRadioButtons.stories.tsx","tags":["story"],"kind":"Forms/Checkbox & Radio Buttons","story":"CheckboxButton","parameters":{"__id":"forms-checkbox-radio-buttons--checkbox-button","docsOnly":false,"fileName":"./src/stories/CheckboxAndRadioButtons.stories.tsx"}},"forms-checkbox-radio-buttons--checkbox-buttons-group":{"id":"forms-checkbox-radio-buttons--checkbox-buttons-group","name":"Checkbox Buttons Group","title":"Forms/Checkbox & Radio Buttons","importPath":"./src/stories/CheckboxAndRadioButtons.stories.tsx","tags":["story"],"kind":"Forms/Checkbox & Radio Buttons","story":"Checkbox Buttons Group","parameters":{"__id":"forms-checkbox-radio-buttons--checkbox-buttons-group","docsOnly":false,"fileName":"./src/stories/CheckboxAndRadioButtons.stories.tsx"}},"forms-checkbox-radio-buttons--radio-buttons-group":{"id":"forms-checkbox-radio-buttons--radio-buttons-group","name":"Radio Buttons Group","title":"Forms/Checkbox & Radio Buttons","importPath":"./src/stories/CheckboxAndRadioButtons.stories.tsx","tags":["story"],"kind":"Forms/Checkbox & Radio Buttons","story":"Radio Buttons Group","parameters":{"__id":"forms-checkbox-radio-buttons--radio-buttons-group","docsOnly":false,"fileName":"./src/stories/CheckboxAndRadioButtons.stories.tsx"}},"cityblock--city-block":{"id":"cityblock--city-block","name":"City Block","title":"CityBlock","importPath":"./src/stories/CityBlock.stories.tsx","tags":["story"],"kind":"CityBlock","story":"City Block","parameters":{"__id":"cityblock--city-block","docsOnly":false,"fileName":"./src/stories/CityBlock.stories.tsx"}},"cityblock--city-block-examples":{"id":"cityblock--city-block-examples","name":"City Block Examples","title":"CityBlock","importPath":"./src/stories/CityBlock.stories.tsx","tags":["story"],"kind":"CityBlock","story":"City Block Examples","parameters":{"__id":"cityblock--city-block-examples","docsOnly":false,"fileName":"./src/stories/CityBlock.stories.tsx"}},"contactbubble--contact-bubble":{"id":"contactbubble--contact-bubble","name":"Contact Bubble","title":"ContactBubble","importPath":"./src/stories/ContactBubble.stories.tsx","tags":["story"],"kind":"ContactBubble","story":"Contact Bubble","parameters":{"__id":"contactbubble--contact-bubble","docsOnly":false,"fileName":"./src/stories/ContactBubble.stories.tsx"}},"contentarticle--content-article":{"id":"contentarticle--content-article","name":"Content Article","title":"ContentArticle","importPath":"./src/stories/ContentArticle.stories.tsx","tags":["story"],"kind":"ContentArticle","story":"Content Article","parameters":{"__id":"contentarticle--content-article","docsOnly":false,"fileName":"./src/stories/ContentArticle.stories.tsx"}},"contentimage--content-image":{"id":"contentimage--content-image","name":"Content Image","title":"ContentImage","importPath":"./src/stories/ContentImage.stories.tsx","tags":["story"],"kind":"ContentImage","story":"Content Image","parameters":{"__id":"contentimage--content-image","docsOnly":false,"fileName":"./src/stories/ContentImage.stories.tsx"}},"contextmenu--context-menu":{"id":"contextmenu--context-menu","name":"Context Menu","title":"ContextMenu","importPath":"./src/stories/ContextMenu.stories.tsx","tags":["story"],"kind":"ContextMenu","story":"Context Menu","parameters":{"__id":"contextmenu--context-menu","docsOnly":false,"fileName":"./src/stories/ContextMenu.stories.tsx"}},"forms-datepicker--server-text-input":{"id":"forms-datepicker--server-text-input","name":"Server Text Input","title":"Forms/Datepicker","importPath":"./src/stories/Datepicker.stories.tsx","tags":["story"],"kind":"Forms/Datepicker","story":"Server Text Input","parameters":{"__id":"forms-datepicker--server-text-input","docsOnly":false,"fileName":"./src/stories/Datepicker.stories.tsx"}},"forms-datepicker--client-text-input":{"id":"forms-datepicker--client-text-input","name":"Client Text Input","title":"Forms/Datepicker","importPath":"./src/stories/Datepicker.stories.tsx","tags":["story"],"kind":"Forms/Datepicker","story":"Client Text Input","parameters":{"__id":"forms-datepicker--client-text-input","docsOnly":false,"fileName":"./src/stories/Datepicker.stories.tsx"}},"dropdownbutton--dropdown-button":{"id":"dropdownbutton--dropdown-button","name":"Dropdown Button","title":"DropdownButton","importPath":"./src/stories/DropdownButton.stories.tsx","tags":["story"],"kind":"DropdownButton","story":"Dropdown Button","parameters":{"__id":"dropdownbutton--dropdown-button","docsOnly":false,"fileName":"./src/stories/DropdownButton.stories.tsx"}},"extralinks--extra-links":{"id":"extralinks--extra-links","name":"Extra Links","title":"ExtraLinks","importPath":"./src/stories/ExtraLinks.stories.tsx","tags":["story"],"kind":"ExtraLinks","story":"Extra Links","parameters":{"__id":"extralinks--extra-links","docsOnly":false,"fileName":"./src/stories/ExtraLinks.stories.tsx"}},"featurelist--feature-list":{"id":"featurelist--feature-list","name":"Feature List","title":"FeatureList","importPath":"./src/stories/FeatureList.stories.tsx","tags":["story"],"kind":"FeatureList","story":"Feature List","parameters":{"__id":"featurelist--feature-list","docsOnly":false,"fileName":"./src/stories/FeatureList.stories.tsx"}},"forms-fieldgroup--field-group":{"id":"forms-fieldgroup--field-group","name":"Field Group","title":"Forms/FieldGroup","importPath":"./src/stories/FieldGroup.stories.tsx","tags":["story"],"kind":"Forms/FieldGroup","story":"Field Group","parameters":{"__id":"forms-fieldgroup--field-group","docsOnly":false,"fileName":"./src/stories/FieldGroup.stories.tsx"}},"forms-fileinput--file-input":{"id":"forms-fileinput--file-input","name":"File Input","title":"Forms/FileInput","importPath":"./src/stories/FileInput.stories.tsx","tags":["story"],"kind":"Forms/FileInput","story":"File Input","parameters":{"__id":"forms-fileinput--file-input","docsOnly":false,"fileName":"./src/stories/FileInput.stories.tsx"}},"layout-footerbadges--footer-badges":{"id":"layout-footerbadges--footer-badges","name":"Footer Badges","title":"Layout/FooterBadges","importPath":"./src/stories/FooterBadges.stories.tsx","tags":["story"],"kind":"Layout/FooterBadges","story":"Footer Badges","parameters":{"__id":"layout-footerbadges--footer-badges","docsOnly":false,"fileName":"./src/stories/FooterBadges.stories.tsx"}},"layout-footerinfo--footer-info":{"id":"layout-footerinfo--footer-info","name":"Footer Info","title":"Layout/FooterInfo","importPath":"./src/stories/FooterInfo.stories.tsx","tags":["story"],"kind":"Layout/FooterInfo","story":"Footer Info","parameters":{"__id":"layout-footerinfo--footer-info","docsOnly":false,"fileName":"./src/stories/FooterInfo.stories.tsx"}},"footnote--footnote":{"id":"footnote--footnote","name":"Footnote","title":"Footnote","importPath":"./src/stories/Footnote.stories.tsx","tags":["story"],"kind":"Footnote","story":"Footnote","parameters":{"__id":"footnote--footnote","docsOnly":false,"fileName":"./src/stories/Footnote.stories.tsx"}},"forms-formfield--form-field":{"id":"forms-formfield--form-field","name":"Form Field","title":"Forms/FormField","importPath":"./src/stories/FormField.stories.tsx","tags":["story"],"kind":"Forms/FormField","story":"Form Field","parameters":{"__id":"forms-formfield--form-field","docsOnly":false,"fileName":"./src/stories/FormField.stories.tsx"}},"gallery--gallery":{"id":"gallery--gallery","name":"Gallery","title":"Gallery","importPath":"./src/stories/Gallery.stories.tsx","tags":["story"],"kind":"Gallery","story":"Gallery","parameters":{"__id":"gallery--gallery","docsOnly":false,"fileName":"./src/stories/Gallery.stories.tsx"}},"gridblocks--grid-blocks":{"id":"gridblocks--grid-blocks","name":"Grid Blocks","title":"GridBlocks","importPath":"./src/stories/GridBlocks.stories.tsx","tags":["story"],"kind":"GridBlocks","story":"Grid Blocks","parameters":{"__id":"gridblocks--grid-blocks","docsOnly":false,"fileName":"./src/stories/GridBlocks.stories.tsx"}},"text-heading--heading":{"id":"text-heading--heading","name":"Heading","title":"text/Heading","importPath":"./src/stories/Heading.stories.tsx","tags":["story"],"kind":"text/Heading","story":"Heading","parameters":{"__id":"text-heading--heading","docsOnly":false,"fileName":"./src/stories/Heading.stories.tsx"}},"heroblock--hero-block":{"id":"heroblock--hero-block","name":"Hero Block","title":"HeroBlock","importPath":"./src/stories/HeroBlock.stories.tsx","tags":["story"],"kind":"HeroBlock","story":"Hero Block","parameters":{"__id":"heroblock--hero-block","docsOnly":false,"fileName":"./src/stories/HeroBlock.stories.tsx"}},"heroblock--hero-block-examples":{"id":"heroblock--hero-block-examples","name":"Hero Block Examples","title":"HeroBlock","importPath":"./src/stories/HeroBlock.stories.tsx","tags":["story"],"kind":"HeroBlock","story":"Hero Block Examples","parameters":{"__id":"heroblock--hero-block-examples","docsOnly":false,"fileName":"./src/stories/HeroBlock.stories.tsx"}},"misc-homepage--search-hero-paragraph":{"id":"misc-homepage--search-hero-paragraph","name":"Search Hero Paragraph","title":"_misc/HomePage","importPath":"./src/stories/HomePage/HomePage.stories.tsx","tags":["story"],"kind":"_misc/HomePage","story":"Search Hero Paragraph","parameters":{"__id":"misc-homepage--search-hero-paragraph","docsOnly":false,"fileName":"./src/stories/HomePage/HomePage.stories.tsx"}},"misc-homepage--home-page":{"id":"misc-homepage--home-page","name":"Home Page","title":"_misc/HomePage","importPath":"./src/stories/HomePage/Layout--HomePage.stories.tsx","tags":["story"],"kind":"_misc/HomePage","story":"Home Page","parameters":{"__id":"misc-homepage--home-page","docsOnly":false,"fileName":"./src/stories/HomePage/Layout--HomePage.stories.tsx"}},"icon--icon":{"id":"icon--icon","name":"Icon","title":"Icon","importPath":"./src/stories/Icon.stories.tsx","tags":["story"],"kind":"Icon","story":"Icon","parameters":{"__id":"icon--icon","docsOnly":false,"fileName":"./src/stories/Icon.stories.tsx"}},"iframeblock--iframe-block":{"id":"iframeblock--iframe-block","name":"Iframe Block","title":"IframeBlock","importPath":"./src/stories/IframeBlock.stories.tsx","tags":["story"],"kind":"IframeBlock","story":"Iframe Block","parameters":{"__id":"iframeblock--iframe-block","docsOnly":false,"fileName":"./src/stories/IframeBlock.stories.tsx"}},"iframedlayout--iframed-layout":{"id":"iframedlayout--iframed-layout","name":"Iframed Layout","title":"IframedLayout","importPath":"./src/stories/IframedLayout.stories.tsx","tags":["story"],"kind":"IframedLayout","story":"Iframed Layout","parameters":{"__id":"iframedlayout--iframed-layout","docsOnly":false,"fileName":"./src/stories/IframedLayout.stories.tsx"}},"imagecards--image-cards":{"id":"imagecards--image-cards","name":"Image Cards","title":"ImageCards","importPath":"./src/stories/ImageCards.stories.tsx","tags":["story"],"kind":"ImageCards","story":"Image Cards","parameters":{"__id":"imagecards--image-cards","docsOnly":false,"fileName":"./src/stories/ImageCards.stories.tsx"}},"infoblock--info-block":{"id":"infoblock--info-block","name":"Info Block","title":"InfoBlock","importPath":"./src/stories/InfoBlocks.stories.tsx","tags":["story"],"kind":"InfoBlock","story":"Info Block","parameters":{"__id":"infoblock--info-block","docsOnly":false,"fileName":"./src/stories/InfoBlocks.stories.tsx"}},"infohero--info-hero":{"id":"infohero--info-hero","name":"Info Hero","title":"InfoHero","importPath":"./src/stories/InfoHero.stories.tsx","tags":["story"],"kind":"InfoHero","story":"Info Hero","parameters":{"__id":"infohero--info-hero","docsOnly":false,"fileName":"./src/stories/InfoHero.stories.tsx"}},"islandblock--island-block":{"id":"islandblock--island-block","name":"Island Block","title":"IslandBlock","importPath":"./src/stories/IslandBlock.stories.tsx","tags":["story"],"kind":"IslandBlock","story":"Island Block","parameters":{"__id":"islandblock--island-block","docsOnly":false,"fileName":"./src/stories/IslandBlock.stories.tsx"}},"islandblock--island-block-examples":{"id":"islandblock--island-block-examples","name":"Island Block Examples","title":"IslandBlock","importPath":"./src/stories/IslandBlock.stories.tsx","tags":["story"],"kind":"IslandBlock","story":"Island Block Examples","parameters":{"__id":"islandblock--island-block-examples","docsOnly":false,"fileName":"./src/stories/IslandBlock.stories.tsx"}},"labeledtextblock--labeled-text-block":{"id":"labeledtextblock--labeled-text-block","name":"Labeled Text Block","title":"LabeledTextBlock","importPath":"./src/stories/LabeledTextBlock.stories.tsx","tags":["story"],"kind":"LabeledTextBlock","story":"Labeled Text Block","parameters":{"__id":"labeledtextblock--labeled-text-block","docsOnly":false,"fileName":"./src/stories/LabeledTextBlock.stories.tsx"}},"labeledtextblock--labeled-text-block-examples":{"id":"labeledtextblock--labeled-text-block-examples","name":"Labeled Text Block Examples","title":"LabeledTextBlock","importPath":"./src/stories/LabeledTextBlock.stories.tsx","tags":["story"],"kind":"LabeledTextBlock","story":"Labeled Text Block Examples","parameters":{"__id":"labeledtextblock--labeled-text-block-examples","docsOnly":false,"fileName":"./src/stories/LabeledTextBlock.stories.tsx"}},"layout--layout-with-content":{"id":"layout--layout-with-content","name":"Layout With Content","title":"Layout","importPath":"./src/stories/Layout.stories.tsx","tags":["story"],"kind":"Layout","story":"Layout With Content","parameters":{"__id":"layout--layout-with-content","docsOnly":false,"fileName":"./src/stories/Layout.stories.tsx"}},"layout--minimal-layout":{"id":"layout--minimal-layout","name":"Minimal Layout","title":"Layout","importPath":"./src/stories/Layout.stories.tsx","tags":["story"],"kind":"Layout","story":"Minimal Layout","parameters":{"__id":"layout--minimal-layout","docsOnly":false,"fileName":"./src/stories/Layout.stories.tsx"}},"layout-mainmenu--main-menu":{"id":"layout-mainmenu--main-menu","name":"Main Menu","title":"Layout/MainMenu","importPath":"./src/stories/Mainmenu.stories.tsx","tags":["story"],"kind":"Layout/MainMenu","story":"Main Menu","parameters":{"__id":"layout-mainmenu--main-menu","docsOnly":false,"fileName":"./src/stories/Mainmenu.stories.tsx"}},"layout-mainmenu--mega-menu":{"id":"layout-mainmenu--mega-menu","name":"Mega Menu","title":"Layout/MainMenu","importPath":"./src/stories/Mainmenu.stories.tsx","tags":["story"],"kind":"Layout/MainMenu","story":"Mega Menu","parameters":{"__id":"layout-mainmenu--mega-menu","docsOnly":false,"fileName":"./src/stories/Mainmenu.stories.tsx"}},"layout-mainmenu2--main-menu-2":{"id":"layout-mainmenu2--main-menu-2","name":"Main Menu 2","title":"Layout/MainMenu2","importPath":"./src/stories/Mainmenu2.stories.tsx","tags":["story"],"kind":"Layout/MainMenu2","story":"Main Menu 2","parameters":{"__id":"layout-mainmenu2--main-menu-2","docsOnly":false,"fileName":"./src/stories/Mainmenu2.stories.tsx"}},"minimetrics--mini-metrics":{"id":"minimetrics--mini-metrics","name":"Mini Metrics","title":"MiniMetrics","importPath":"./src/stories/MiniMetrics.stories.tsx","tags":["story"],"kind":"MiniMetrics","story":"Mini Metrics","parameters":{"__id":"minimetrics--mini-metrics","docsOnly":false,"fileName":"./src/stories/MiniMetrics.stories.tsx"}},"modal--modal":{"id":"modal--modal","name":"Modal","title":"Modal","importPath":"./src/stories/Modal.stories.tsx","tags":["story"],"kind":"Modal","story":"Modal","parameters":{"__id":"modal--modal","docsOnly":false,"fileName":"./src/stories/Modal.stories.tsx"}},"modal--modal-dynamics":{"id":"modal--modal-dynamics","name":"Modal Dynamics","title":"Modal","importPath":"./src/stories/Modal.stories.tsx","tags":["story"],"kind":"Modal","story":"Modal Dynamics","parameters":{"__id":"modal--modal-dynamics","docsOnly":false,"fileName":"./src/stories/Modal.stories.tsx"}},"forms-multiselect--multiselect":{"id":"forms-multiselect--multiselect","name":"Multiselect","title":"Forms/Multiselect","importPath":"./src/stories/Multiselect.stories.tsx","tags":["story"],"kind":"Forms/Multiselect","story":"Multiselect","parameters":{"__id":"forms-multiselect--multiselect","docsOnly":false,"fileName":"./src/stories/Multiselect.stories.tsx"}},"namecards--name-cards":{"id":"namecards--name-cards","name":"Name Cards","title":"NameCards","importPath":"./src/stories/NameCards.stories.tsx","tags":["story"],"kind":"NameCards","story":"Name Cards","parameters":{"__id":"namecards--name-cards","docsOnly":false,"fileName":"./src/stories/NameCards.stories.tsx"}},"newshero--news-hero":{"id":"newshero--news-hero","name":"News Hero","title":"NewsHero","importPath":"./src/stories/NewsHero.stories.tsx","tags":["story"],"kind":"NewsHero","story":"News Hero","parameters":{"__id":"newshero--news-hero","docsOnly":false,"fileName":"./src/stories/NewsHero.stories.tsx"}},"newshero--news-hero-examples":{"id":"newshero--news-hero-examples","name":"News Hero Examples","title":"NewsHero","importPath":"./src/stories/NewsHero.stories.tsx","tags":["story"],"kind":"NewsHero","story":"News Hero Examples","parameters":{"__id":"newshero--news-hero-examples","docsOnly":false,"fileName":"./src/stories/NewsHero.stories.tsx"}},"misc-reykjavik-is--news-list-paragraph":{"id":"misc-reykjavik-is--news-list-paragraph","name":"News List Paragraph","title":"_misc/reykjavik-is","importPath":"./src/stories/NewsListParagraph.stories.tsx","tags":["story"],"kind":"_misc/reykjavik-is","story":"News List Paragraph","parameters":{"__id":"misc-reykjavik-is--news-list-paragraph","docsOnly":false,"fileName":"./src/stories/NewsListParagraph.stories.tsx"}},"pagefilter--page-filter":{"id":"pagefilter--page-filter","name":"Page Filter","title":"PageFilter","importPath":"./src/stories/PageFilter.stories.tsx","tags":["story"],"kind":"PageFilter","story":"Page Filter","parameters":{"__id":"pagefilter--page-filter","docsOnly":false,"fileName":"./src/stories/PageFilter.stories.tsx"}},"text-pageheading--page-heading":{"id":"text-pageheading--page-heading","name":"Page Heading","title":"text/PageHeading","importPath":"./src/stories/PageHeading.stories.tsx","tags":["story"],"kind":"text/PageHeading","story":"Page Heading","parameters":{"__id":"text-pageheading--page-heading","docsOnly":false,"fileName":"./src/stories/PageHeading.stories.tsx"}},"pagination--pagination":{"id":"pagination--pagination","name":"Pagination","title":"Pagination","importPath":"./src/stories/Pagination.stories.tsx","tags":["story"],"kind":"Pagination","story":"Pagination","parameters":{"__id":"pagination--pagination","docsOnly":false,"fileName":"./src/stories/Pagination.stories.tsx"}},"picture--picture":{"id":"picture--picture","name":"Picture","title":"Picture","importPath":"./src/stories/Picture.stories.tsx","tags":["story"],"kind":"Picture","story":"Picture","parameters":{"__id":"picture--picture","docsOnly":false,"fileName":"./src/stories/Picture.stories.tsx"}},"processoverview--process-overview":{"id":"processoverview--process-overview","name":"Process Overview","title":"ProcessOverview","importPath":"./src/stories/ProcessOverview.stories.tsx","tags":["story"],"kind":"ProcessOverview","story":"Process Overview","parameters":{"__id":"processoverview--process-overview","docsOnly":false,"fileName":"./src/stories/ProcessOverview.stories.tsx"}},"text-pullquote--pull-quote":{"id":"text-pullquote--pull-quote","name":"Pull Quote","title":"text/PullQuote","importPath":"./src/stories/PullQuote.stories.tsx","tags":["story"],"kind":"text/PullQuote","story":"Pull Quote","parameters":{"__id":"text-pullquote--pull-quote","docsOnly":false,"fileName":"./src/stories/PullQuote.stories.tsx"}},"readspeakerplayer--read-speaker-player":{"id":"readspeakerplayer--read-speaker-player","name":"Read Speaker Player","title":"ReadSpeakerPlayer","importPath":"./src/stories/ReadSpeakerPlayer.stories.tsx","tags":["story"],"kind":"ReadSpeakerPlayer","story":"Read Speaker Player","parameters":{"__id":"readspeakerplayer--read-speaker-player","docsOnly":false,"fileName":"./src/stories/ReadSpeakerPlayer.stories.tsx"}},"relatedlinks--related-links":{"id":"relatedlinks--related-links","name":"Related Links","title":"RelatedLinks","importPath":"./src/stories/RelatedLinks.stories.tsx","tags":["story"],"kind":"RelatedLinks","story":"Related Links","parameters":{"__id":"relatedlinks--related-links","docsOnly":false,"fileName":"./src/stories/RelatedLinks.stories.tsx"}},"reykjavikwaves--reykjavik-waves":{"id":"reykjavikwaves--reykjavik-waves","name":"Reykjavik Waves","title":"ReykjavikWaves","importPath":"./src/stories/ReykjavikWaves.stories.tsx","tags":["story"],"kind":"ReykjavikWaves","story":"Reykjavik Waves","parameters":{"__id":"reykjavikwaves--reykjavik-waves","docsOnly":false,"fileName":"./src/stories/ReykjavikWaves.stories.tsx"}},"grid--row-block":{"id":"grid--row-block","name":"Row Block","title":"Grid","importPath":"./src/stories/RowBlock.stories.tsx","tags":["story"],"kind":"Grid","story":"Row Block","parameters":{"__id":"grid--row-block","docsOnly":false,"fileName":"./src/stories/RowBlock.stories.tsx"}},"forms-searchinput--search-input":{"id":"forms-searchinput--search-input","name":"Search Input","title":"Forms/SearchInput","importPath":"./src/stories/SearchInput.stories.tsx","tags":["story"],"kind":"Forms/SearchInput","story":"Search Input","parameters":{"__id":"forms-searchinput--search-input","docsOnly":false,"fileName":"./src/stories/SearchInput.stories.tsx"}},"searchresults--search-results":{"id":"searchresults--search-results","name":"Search Results","title":"SearchResults","importPath":"./src/stories/SearchResults.stories.tsx","tags":["story"],"kind":"SearchResults","story":"Search Results","parameters":{"__id":"searchresults--search-results","docsOnly":false,"fileName":"./src/stories/SearchResults.stories.tsx"}},"forms-selectbox--selectbox-server":{"id":"forms-selectbox--selectbox-server","name":"Selectbox Server","title":"Forms/Selectbox","importPath":"./src/stories/Selectbox.stories.tsx","tags":["story"],"kind":"Forms/Selectbox","story":"Selectbox Server","parameters":{"__id":"forms-selectbox--selectbox-server","docsOnly":false,"fileName":"./src/stories/Selectbox.stories.tsx"}},"forms-selectbox--selectbox-client":{"id":"forms-selectbox--selectbox-client","name":"Selectbox Client","title":"Forms/Selectbox","importPath":"./src/stories/Selectbox.stories.tsx","tags":["story"],"kind":"Forms/Selectbox","story":"Selectbox Client","parameters":{"__id":"forms-selectbox--selectbox-client","docsOnly":false,"fileName":"./src/stories/Selectbox.stories.tsx"}},"sharebuttons--share-buttons":{"id":"sharebuttons--share-buttons","name":"Share Buttons","title":"ShareButtons","importPath":"./src/stories/ShareButtons.stories.tsx","tags":["story"],"kind":"ShareButtons","story":"Share Buttons","parameters":{"__id":"sharebuttons--share-buttons","docsOnly":false,"fileName":"./src/stories/ShareButtons.stories.tsx"}},"sharpie--sharpie":{"id":"sharpie--sharpie","name":"Sharpie","title":"Sharpie","importPath":"./src/stories/Sharpie.stories.tsx","tags":["story"],"kind":"Sharpie","story":"Sharpie","parameters":{"__id":"sharpie--sharpie","docsOnly":false,"fileName":"./src/stories/Sharpie.stories.tsx"}},"forms-site-search-autocomplete--site-search-autocomplete":{"id":"forms-site-search-autocomplete--site-search-autocomplete","name":"Site Search Autocomplete","title":"Forms/Site Search Autocomplete","importPath":"./src/stories/SiteSearchAutoComplete.stories.tsx","tags":["story"],"kind":"Forms/Site Search Autocomplete","story":"Site Search Autocomplete","parameters":{"__id":"forms-site-search-autocomplete--site-search-autocomplete","docsOnly":false,"fileName":"./src/stories/SiteSearchAutoComplete.stories.tsx"}},"forms-sitesearchinput--site-search-input":{"id":"forms-sitesearchinput--site-search-input","name":"Site Search Input","title":"Forms/SiteSearchInput","importPath":"./src/stories/SiteSearchInput.stories.tsx","tags":["story"],"kind":"Forms/SiteSearchInput","story":"Site Search Input","parameters":{"__id":"forms-sitesearchinput--site-search-input","docsOnly":false,"fileName":"./src/stories/SiteSearchInput.stories.tsx"}},"skeleton--skeleton":{"id":"skeleton--skeleton","name":"Skeleton","title":"Skeleton","importPath":"./src/stories/Skeleton.stories.tsx","tags":["story"],"kind":"Skeleton","story":"Skeleton","parameters":{"__id":"skeleton--skeleton","docsOnly":false,"fileName":"./src/stories/Skeleton.stories.tsx"}},"text-subheading--sub-heading":{"id":"text-subheading--sub-heading","name":"Sub Heading","title":"text/SubHeading","importPath":"./src/stories/SubHeading.stories.tsx","tags":["story"],"kind":"text/SubHeading","story":"Sub Heading","parameters":{"__id":"text-subheading--sub-heading","docsOnly":false,"fileName":"./src/stories/SubHeading.stories.tsx"}},"tabs--tabs":{"id":"tabs--tabs","name":"Tabs","title":"Tabs","importPath":"./src/stories/Tabs.stories.tsx","tags":["story"],"kind":"Tabs","story":"Tabs","parameters":{"__id":"tabs--tabs","docsOnly":false,"fileName":"./src/stories/Tabs.stories.tsx"}},"tabs--tabs-anchors":{"id":"tabs--tabs-anchors","name":"Tabs Anchors","title":"Tabs","importPath":"./src/stories/Tabs.stories.tsx","tags":["story"],"kind":"Tabs","story":"Tabs Anchors","parameters":{"__id":"tabs--tabs-anchors","docsOnly":false,"fileName":"./src/stories/Tabs.stories.tsx"}},"tagpill--tag-pill":{"id":"tagpill--tag-pill","name":"Tag Pill","title":"TagPill","importPath":"./src/stories/TagPill.stories.tsx","tags":["story"],"kind":"TagPill","story":"Tag Pill","parameters":{"__id":"tagpill--tag-pill","docsOnly":false,"fileName":"./src/stories/TagPill.stories.tsx"}},"text-textblock--text-block":{"id":"text-textblock--text-block","name":"Text Block","title":"text/TextBlock","importPath":"./src/stories/TextBlock.stories.tsx","tags":["story"],"kind":"text/TextBlock","story":"Text Block","parameters":{"__id":"text-textblock--text-block","docsOnly":false,"fileName":"./src/stories/TextBlock.stories.tsx"}},"buttons-textbuttons--text-buttons":{"id":"buttons-textbuttons--text-buttons","name":"Text Buttons","title":"buttons/TextButtons","importPath":"./src/stories/TextButton.stories.tsx","tags":["story"],"kind":"buttons/TextButtons","story":"Text Buttons","parameters":{"__id":"buttons-textbuttons--text-buttons","docsOnly":false,"fileName":"./src/stories/TextButton.stories.tsx"}},"forms-textinput--server-text-input":{"id":"forms-textinput--server-text-input","name":"Server Text Input","title":"Forms/TextInput","importPath":"./src/stories/TextInput.stories.tsx","tags":["story"],"kind":"Forms/TextInput","story":"Server Text Input","parameters":{"__id":"forms-textinput--server-text-input","docsOnly":false,"fileName":"./src/stories/TextInput.stories.tsx"}},"forms-textinput--client-text-input":{"id":"forms-textinput--client-text-input","name":"Client Text Input","title":"Forms/TextInput","importPath":"./src/stories/TextInput.stories.tsx","tags":["story"],"kind":"Forms/TextInput","story":"Client Text Input","parameters":{"__id":"forms-textinput--client-text-input","docsOnly":false,"fileName":"./src/stories/TextInput.stories.tsx"}},"tooltip--tooltip":{"id":"tooltip--tooltip","name":"Tooltip","title":"Tooltip","importPath":"./src/stories/Tooltip.stories.tsx","tags":["story"],"kind":"Tooltip","story":"Tooltip","parameters":{"__id":"tooltip--tooltip","docsOnly":false,"fileName":"./src/stories/Tooltip.stories.tsx"}},"vspacer--v-spacer":{"id":"vspacer--v-spacer","name":"V Spacer","title":"VSpacer","importPath":"./src/stories/VSpacer.stories.tsx","tags":["story"],"kind":"VSpacer","story":"V Spacer","parameters":{"__id":"vspacer--v-spacer","docsOnly":false,"fileName":"./src/stories/VSpacer.stories.tsx"}},"layout-wizardlayout--minimal-wizard-layout":{"id":"layout-wizardlayout--minimal-wizard-layout","name":"Minimal Wizard Layout","title":"Layout/WizardLayout","importPath":"./src/stories/WizardLayout.stories.tsx","tags":["story"],"kind":"Layout/WizardLayout","story":"Minimal Wizard Layout","parameters":{"__id":"layout-wizardlayout--minimal-wizard-layout","docsOnly":false,"fileName":"./src/stories/WizardLayout.stories.tsx"}},"layout-wizardlayout--wizard-layout-with-content":{"id":"layout-wizardlayout--wizard-layout-with-content","name":"Wizard Layout With Content","title":"Layout/WizardLayout","importPath":"./src/stories/WizardLayout.stories.tsx","tags":["story"],"kind":"Layout/WizardLayout","story":"Wizard Layout With Content","parameters":{"__id":"layout-wizardlayout--wizard-layout-with-content","docsOnly":false,"fileName":"./src/stories/WizardLayout.stories.tsx"}},"wizardstepper--wizard-stepper":{"id":"wizardstepper--wizard-stepper","name":"Wizard Stepper","title":"WizardStepper","importPath":"./src/stories/WizardStepper.stories.tsx","tags":["story"],"kind":"WizardStepper","story":"Wizard Stepper","parameters":{"__id":"wizardstepper--wizard-stepper","docsOnly":false,"fileName":"./src/stories/WizardStepper.stories.tsx"}}}}
